CCMetagen-1.5.0.data/scripts/CCMetagen.py
CCMetagen-1.5.0.data/scripts/CCMetagen_extract_seqs.py
CCMetagen-1.5.0.data/scripts/CCMetagen_merge.py
ccmetagen/__init__.py
ccmetagen/cTaxInfo.py
ccmetagen/fNCBItax.py
ccmetagen/fParseKMA.py
CCMetagen-1.5.0.dist-info/AUTHORS.md
CCMetagen-1.5.0.dist-info/LICENSE
CCMetagen-1.5.0.dist-info/METADATA
CCMetagen-1.5.0.dist-info/WHEEL
CCMetagen-1.5.0.dist-info/top_level.txt
CCMetagen-1.5.0.dist-info/RECORD
