Metadata-Version: 2.1
Name: CCMetagen
Version: 1.5.0
Summary: Microbiome classification pipeline
Home-page: https://github.com/vrmarcelino/CCMetagen.git
Author: Vanessa R. Marcelino Jan P. Buchmann Andreas Sjödin Philip T.L.C. Clausen
Author-email: vrmarcelino@gmail.com
License: GPL-3.0
Project-URL: Source, https://github.com/vrmarcelino/CCMetagen.git
Project-URL: Preprint, https://www.biorxiv.org/content/10.1101/641332v2
Keywords: bioinformatics taxonomy metagenomic classifier KMA
Classifier: Programming Language :: Python :: 3.9
Classifier: Operating System :: POSIX :: Linux
Classifier: Development Status :: 5 - Production/Stable
Classifier: Environment :: Console
Classifier: Intended Audience :: Science/Research
Classifier: License :: OSI Approved :: GNU General Public License v3 (GPLv3)
Classifier: Topic :: Scientific/Engineering :: Bio-Informatics
Requires-Python: >=3.9
License-File: LICENSE
License-File: AUTHORS.md
Requires-Dist: pandas
Requires-Dist: ete3
